cdvl_crawler/__init__.py
cdvl_crawler/__main__.py
cdvl_crawler/crawler.py
cdvl_crawler/downloader.py
cdvl_crawler/exporter.py
cdvl_crawler/generator.py
cdvl_crawler/py.typed
cdvl_crawler/types.py
cdvl_crawler/utils.py
cdvl_crawler-0.7.2.dist-info/WHEEL
cdvl_crawler-0.7.2.dist-info/entry_points.txt
cdvl_crawler-0.7.2.dist-info/METADATA
cdvl_crawler-0.7.2.dist-info/RECORD
