Metadata-Version: 2.4
Name: cdvl-crawler
Version: 0.7.2
Summary: Crawl and download videos from the CDVL (Consumer Digital Video Library) research repository
Keywords: cdvl,video,crawler,downloader,research
Author: Werner Robitza
Author-email: Werner Robitza <werner.robitza@gmail.com>
License-Expression: MIT
Classifier: Development Status :: 4 - Beta
Classifier: Intended Audience :: Developers
Classifier: Intended Audience :: Science/Research
Classifier: Topic :: Multimedia :: Video
Classifier: Topic :: Internet :: WWW/HTTP :: Indexing/Search
Classifier: Natural Language :: English
Classifier: Programming Language :: Python :: 3
Classifier: Programming Language :: Python :: 3.9
Classifier: Programming Language :: Python :: 3.10
Classifier: Programming Language :: Python :: 3.11
Classifier: Programming Language :: Python :: 3.12
Classifier: Programming Language :: Python :: 3.13
Classifier: Programming Language :: Python :: 3.14
Requires-Dist: aiohttp>=3.9.0
Requires-Dist: beautifulsoup4>=4.12.0
Requires-Dist: lxml>=5.0.0
Requires-Dist: tqdm>=4.66.0
Requires-Python: >=3.9
Project-URL: Homepage, https://github.com/slhck/cdvl-crawler
Project-URL: Repository, https://github.com/slhck/cdvl-crawler
